[
{"_creationTime":1691013604325.0217,"_id":"2w1tjesf0ng55yvwzv5gkehv9hsy20r","pushDate":"2023-05-11 19:22:54.225434","url":"https://go.cvx.is/backend_release/0.0.358","version":"0.0.358"},
{"_creationTime":1691013604325.0137,"_id":"2w4w1wx9f0bpgm1adt0w6j689hspwq8","pushDate":"2023-06-22 21:11:43.473605","url":"https://go.cvx.is/backend_release/0.0.390","version":"0.0.390"},
{"_creationTime":1691013604325.0095,"_id":"2w6q24ygyjhsb0mxq619y8v09hsxyeg","pushDate":"2023-07-27 14:46:55.050163","url":"https://go.cvx.is/backend_release/0.0.408","version":"0.0.408"},
{"_creationTime":1691013604325.0125,"_id":"2w7c8t54p3be7gd212vhnabw9hsqwdr","pushDate":"2023-06-30 17:53:18.797499","url":"https://go.cvx.is/backend_release/0.0.395","version":"0.0.395"},
{"_creationTime":1691013604325.0205,"_id":"2w7d7p8ysmtr6njf4yejj0jy9hsjar0","pushDate":"2023-05-19 21:47:51.314069","url":"https://go.cvx.is/backend_release/0.0.363","version":"0.0.363"},
{"_creationTime":1691013604325.0317,"_id":"2waq5fwxpbr2kx6wydrq02zk9hsjcc8","pushDate":"2023-03-01 01:33:13.404102","url":"https://go.cvx.is/backend_release/0.0.310","version":"0.0.310"},
{"_creationTime":1691013604325.0244,"_id":"2wbe3zsmhdwb9zwtc6a6arfr9hsg7dg","pushDate":"2023-04-21 23:28:13.598352","url":"https://go.cvx.is/backend_release/0.0.348","version":"0.0.348"},
{"_creationTime":1691013604325.013,"_id":"2wbhrcq9s7vvqz6d32h1rcdh9hsj1a8","pushDate":"2023-06-27 22:38:38.100953","url":"https://go.cvx.is/backend_release/0.0.393","version":"0.0.393"},
{"_creationTime":1691013604325.0293,"_id":"2wbmecamykwc4313fy9499979hsvf3r","pushDate":"2023-03-20 17:36:13.804152","url":"https://go.cvx.is/backend_release/0.0.323","version":"0.0.323"},
{"_creationTime":1691013604325.0144,"_id":"2wc80w1msnj2n29zmc095vfs9hsn168","pushDate":"2023-06-15 23:10:30.389853","url":"https://go.cvx.is/backend_release/0.0.387","version":"0.0.387"},
{"_creationTime":1691013604325.0305,"_id":"2wj4j1g1mw77t90bxdqy1vs99hszt10","pushDate":"2023-03-14 21:41:36.936841","url":"https://go.cvx.is/backend_release/0.0.317","version":"0.0.317"},
{"_creationTime":1691013604325.01,"_id":"2wp25y1ac19ge6qczw2gb04s9hsjh7g","pushDate":"2023-07-19 13:26:44.253279","url":"https://go.cvx.is/backend_release/0.0.406","version":"0.0.406"},
{"_creationTime":1691013604325.0085,"_id":"2wq7jtz4c8k53qpa72mjtyx09hsqd90","pushDate":"2023-07-31 14:39:23.625178","url":"https://go.cvx.is/backend_release/0.0.414","version":"0.0.414"},
{"_creationTime":1691013604325.016,"_id":"2wr05jfm007me4c0eqx0fcnv9hsryg8","pushDate":"2023-06-09 21:21:42.864806","url":"https://go.cvx.is/backend_release/0.0.383","version":"0.0.383"},
{"_creationTime":1691013604325.0088,"_id":"2wtky7qg7m1kzn1zqdsrgcgm9hsydg8","pushDate":"2023-07-28 21:15:43.272125","url":"https://go.cvx.is/backend_release/0.0.413","version":"0.0.413"},
{"_creationTime":1691013604325.03,"_id":"2wxqa006ts7421335dhecg5q9hsw5br","pushDate":"2023-03-15 21:57:40.666149","url":"https://go.cvx.is/backend_release/0.0.319","version":"0.0.319"},
{"_creationTime":1691013604325.0103,"_id":"2wye2z55ndhpc4pqn385nqbj9hss4j8","pushDate":"2023-07-18 15:59:20.538699","url":"https://go.cvx.is/backend_release/0.0.405","version":"0.0.405"},
{"_creationTime":1691013604325.0232,"_id":"2wyjp3mnw2mv1p4y1445xe0c9hsw7c0","pushDate":"2023-04-27 23:04:54.212814","url":"https://go.cvx.is/backend_release/0.0.351","version":"0.0.351"},
{"_creationTime":1691013604325.0176,"_id":"2wys24sfh9qjy3s4vr1k4y3c9hskgjg","pushDate":"2023-06-02 00:37:13.689187","url":"https://go.cvx.is/backend_release/0.0.377","version":"0.0.377"},
{"_creationTime":1691013604325.0166,"_id":"2wyveqpe4yj90k6np87hryg99hsx4m0","pushDate":"2023-06-06 23:23:25.844507","url":"https://go.cvx.is/backend_release/0.0.381","version":"0.0.381"},
{"_creationTime":1691013604325.0212,"_id":"2wzhvdvk452fd165nqk5s82x9hsyrw0","pushDate":"2023-05-15 22:16:50.668247","url":"https://go.cvx.is/backend_release/0.0.360","version":"0.0.360"},
{"_creationTime":1691013604325.017,"_id":"2wzjzfwbgvy2yq3grvsecj8d9hszym8","pushDate":"2023-06-02 22:14:21.362323","url":"https://go.cvx.is/backend_release/0.0.379","version":"0.0.379"},
{"_creationTime":1691013604325.0083,"_id":"2x0ggy66pjh2yeytrrsgqeb39hshfdr","pushDate":"2023-08-02 00:38:50.678108","url":"https://go.cvx.is/backend_release/0.0.415","version":"0.0.415"},
{"_creationTime":1691013604325.0117,"_id":"2x0yzkyfdxwjj4wcfcpx34669hsj75g","pushDate":"2023-07-06 21:36:25.018304","url":"https://go.cvx.is/backend_release/0.0.397","version":"0.0.397"},
{"_creationTime":1691013604325.0112,"_id":"2x14mck8vwvs4qv6rgraghc09hswmw0","pushDate":"2023-07-10 22:08:32.720557","url":"https://go.cvx.is/backend_release/0.0.401","version":"0.0.401"},
{"_creationTime":1691013604325.0286,"_id":"2x311svb0qj4newr2j4d0b0p9hsv5w0","pushDate":"2023-03-22 22:57:28.696021","url":"https://go.cvx.is/backend_release/0.0.326","version":"0.0.326"},
{"_creationTime":1691013604325.0188,"_id":"2x5j9f4h7dmnfc7qsnd3j2yq9hsqc78","pushDate":"2023-05-26 17:10:09.359996","url":"https://go.cvx.is/backend_release/0.0.369","version":"0.0.369"},
{"_creationTime":1691013604325.018,"_id":"2x91rdjx0j163a98kf60fxjp9hsmkhg","pushDate":"2023-05-31 19:07:29.550553","url":"https://go.cvx.is/backend_release/0.0.375","version":"0.0.375"},
{"_creationTime":1691013604325.021,"_id":"2xbev6g9ttd9s961gag8czd39hsza28","pushDate":"2023-05-16 20:51:03.040654","url":"https://go.cvx.is/backend_release/0.0.361","version":"0.0.361"},
{"_creationTime":1691013604325.0227,"_id":"2xct9bt69s1j252peqz673t49hsrtcr","pushDate":"2023-05-01 21:41:18.559206","url":"https://go.cvx.is/backend_release/0.0.354","version":"0.0.354"},
{"_creationTime":1691013604325.019,"_id":"2xcyedyjtp0xrcej5zksfmyt9hstwfr","pushDate":"2023-05-25 23:05:49.446985","url":"https://go.cvx.is/backend_release/0.0.368","version":"0.0.368"},
{"_creationTime":1691013604325.0312,"_id":"2xe7bxpgn7jq29vknqbg4sb89hsnkw0","pushDate":"2023-03-07 22:56:27.321762","url":"https://go.cvx.is/backend_release/0.0.313","version":"0.0.313"},
{"_creationTime":1691013604325.009,"_id":"2xehzad0gdf48effdyak4pgq9hsry3g","pushDate":"2023-07-27 22:25:21.182278","url":"https://go.cvx.is/backend_release/0.0.410","version":"0.0.410"},
{"_creationTime":1691013604325.0105,"_id":"2xfa846cnnyvzbyrsy1gype99hstfsr","pushDate":"2023-07-15 06:25:53.852731","url":"https://go.cvx.is/backend_release/0.0.404","version":"0.0.404"},
{"_creationTime":1691013604325.0154,"_id":"2xgek8hpc18ztq96t5g0thds9hsp970","pushDate":"2023-06-15 00:50:35.277469","url":"https://go.cvx.is/backend_release/0.0.387","version":"0.0.387"},
{"_creationTime":1691013604325.012,"_id":"2xgv14p7w1gkcy1tjexsa7j29hstrsg","pushDate":"2023-07-03 19:01:13.395430","url":"https://go.cvx.is/backend_release/0.0.396","version":"0.0.396"},
{"_creationTime":1691013604325.0107,"_id":"2xgv453xxvpnexn4bp6kd5jn9hsx3gg","pushDate":"2023-07-14 01:04:36.263387","url":"https://go.cvx.is/backend_release/0.0.403","version":"0.0.403"},
{"_creationTime":1691013604325.0298,"_id":"2xh4samf2xnpdhyqtw1wberb9hsthvg","pushDate":"2023-03-16 18:12:25.078281","url":"https://go.cvx.is/backend_release/0.0.321","version":"0.0.321"},
{"_creationTime":1691013604325.0178,"_id":"2xk3atsf1g7rgzmra3fr6px99hsqmq8","pushDate":"2023-06-01 21:06:08.753635","url":"https://go.cvx.is/backend_release/0.0.376","version":"0.0.376"},
{"_creationTime":1691013604325.0098,"_id":"2xksfknzv9eq1cs26g36ae059hsvjf0","pushDate":"2023-07-25 16:20:36.519154","url":"https://go.cvx.is/backend_release/0.0.407","version":"0.0.407"},
{"_creationTime":1691013604325.0093,"_id":"2xmczs9zvqv93h9mapjk2q3f9hsr9x0","pushDate":"2023-07-27 19:15:09.617864","url":"https://go.cvx.is/backend_release/0.0.409","version":"0.0.409"},
{"_creationTime":1691013604325.02,"_id":"2xn6rh9b5h50nqnwkc336n219hssyfg","pushDate":"2023-05-20 00:15:00.499071","url":"https://go.cvx.is/backend_release/0.0.364","version":"0.0.364"},
{"_creationTime":1691013604325.0132,"_id":"2xndh4y122bzf07ybwtmd2zk9hsy0fg","pushDate":"2023-06-23 23:06:56.249013","url":"https://go.cvx.is/backend_release/0.0.392","version":"0.0.392"},
{"_creationTime":1691013604325.0122,"_id":"2xndp0612wzdxeqxc2ck088c9hshrzg","pushDate":"2023-06-30 20:55:39.792661","url":"https://go.cvx.is/backend_release/0.0.394","version":"0.0.394"},
{"_creationTime":1691013604325.0134,"_id":"2xns8pj3t6z5krwa4acwxv8t9hsnf20","pushDate":"2023-06-22 23:20:07.631804","url":"https://go.cvx.is/backend_release/0.0.391","version":"0.0.391"},
{"_creationTime":1691013604325.0127,"_id":"2xr9jdcehnfj8sey2zayzeb69hsyz6r","pushDate":"2023-06-29 18:56:16.539341","url":"https://go.cvx.is/backend_release/0.0.394","version":"0.0.394"},
{"_creationTime":1691013604325.0198,"_id":"2xrkztmwf55ay2wtxg9mdzen9hskn98","pushDate":"2023-05-23 19:50:41.569582","url":"https://go.cvx.is/backend_release/0.0.365","version":"0.0.365"},
{"_creationTime":1691013604325.0203,"_id":"2xs54pwhvkj75fj356v2tqh29hsmakr","pushDate":"2023-05-19 22:10:40.363481","url":"https://go.cvx.is/backend_release/0.0.362","version":"0.0.362"},
{"_creationTime":1691013604325.022,"_id":"2xvbg7d8nw159rk99zkfqvbx9hsv6gr","pushDate":"2023-05-08 19:16:35.702651","url":"https://go.cvx.is/backend_release/0.0.356","version":"0.0.356"},
{"_creationTime":1691013604325.0276,"_id":"2xwx0yr3tjp1p17a6y81fz5w9hsvs08","pushDate":"2023-03-30 21:07:23.109447","url":"https://go.cvx.is/backend_release/0.0.333","version":"0.0.333"},
{"_creationTime":1691013604325.0278,"_id":"2xyn01gs8tcnwqg85bpt0nmh9hsg77r","pushDate":"2023-03-29 20:12:58.722445","url":"https://go.cvx.is/backend_release/0.0.332","version":"0.0.332"},
{"_creationTime":1691013604325.0195,"_id":"2xzx9s2ztrsd3wc6bv40yx659hsjnsg","pushDate":"2023-05-24 23:25:16.503259","url":"https://go.cvx.is/backend_release/0.0.366","version":"0.0.366"},
{"_creationTime":1691013604325.0234,"_id":"2y2kx6x0cv2zbtew55emzstp9hswpxg","pushDate":"2023-04-27 21:23:05.018566","url":"https://go.cvx.is/backend_release/0.0.352","version":"0.0.352"},
{"_creationTime":1691013604325.0322,"_id":"2y3mx1tscy4vhvp7kvaf1kp09hsxgtg","pushDate":"2023-02-27 22:04:58.665676","url":"https://go.cvx.is/backend_release/0.0.306","version":"0.0.306"},
{"_creationTime":1691013604325.0308,"_id":"2y5nama67qbxakxqapy89vyj9hss590","pushDate":"2023-03-13 18:47:37.682543","url":"https://go.cvx.is/backend_release/0.0.316","version":"0.0.316"},
{"_creationTime":1691013604325.0146,"_id":"2y6d414jes350eccs9wc24qj9hst51g","pushDate":"2023-06-15 22:58:59.060652","url":"https://go.cvx.is/backend_release/0.0.385","version":"0.0.385"},
{"_creationTime":1691013604325.0208,"_id":"2y905x3pstxsqqy5h8c6evjv9hspw1g","pushDate":"2023-05-18 22:33:42.302301","url":"https://go.cvx.is/backend_release/0.0.362","version":"0.0.362"},
{"_creationTime":1691013604325.0115,"_id":"2y9jztezedfz1xx5kfhxamty9hsw4rg","pushDate":"2023-07-07 19:32:18.562703","url":"https://go.cvx.is/backend_release/0.0.399","version":"0.0.399"},
{"_creationTime":1691013604325.0254,"_id":"2y9xysemactyftkpybxwmzyz9hspagr","pushDate":"2023-04-12 22:12:51.694160","url":"https://go.cvx.is/backend_release/0.0.341","version":"0.0.341"},
{"_creationTime":1691013604325.0247,"_id":"2yaxat5mrsef50va1w8mqswy9hsmv20","pushDate":"2023-04-20 17:56:52.837720","url":"https://go.cvx.is/backend_release/0.0.347","version":"0.0.347"},
{"_creationTime":1691013604325.0273,"_id":"2ybk6fza3jjqm20j8xh74qsc9hsw9k8","pushDate":"2023-04-03 22:35:39.010658","url":"https://go.cvx.is/backend_release/0.0.334","version":"0.0.334"},
{"_creationTime":1691013604325.0303,"_id":"2yc12p1k92npnevar2dt98919hsmtd8","pushDate":"2023-03-15 01:01:52.206507","url":"https://go.cvx.is/backend_release/0.0.318","version":"0.0.318"},
{"_creationTime":1691013604325.0269,"_id":"2ycjjdwnps279nbh6vrne6b59hsh90r","pushDate":"2023-04-06 21:24:53.771849","url":"https://go.cvx.is/backend_release/0.0.336","version":"0.0.336"},
{"_creationTime":1691013604325.0193,"_id":"2ye8gpf0bzxhrtfdhxycwkea9hsyyqr","pushDate":"2023-05-25 00:02:28.983992","url":"https://go.cvx.is/backend_release/0.0.365","version":"0.0.365"},
{"_creationTime":1691013604325.0242,"_id":"2yewjhqc8jtsxky4e3n825m09hsgjv0","pushDate":"2023-04-22 18:19:01.538313","url":"https://go.cvx.is/backend_release/0.0.349","version":"0.0.349"},
{"_creationTime":1691013604325.031,"_id":"2yfk5waeq7vxhn7e8q1rjpv69hsr5w8","pushDate":"2023-03-09 21:08:39.649054","url":"https://go.cvx.is/backend_release/0.0.315","version":"0.0.315"},
{"_creationTime":1691013604325.015,"_id":"2yj3x2mnn4hen3vs7s13k9079hszhsg","pushDate":"2023-06-15 22:55:39.084200","url":"https://go.cvx.is/backend_release/0.0.387","version":"0.0.387"},
{"_creationTime":1691013604325.028,"_id":"2yjfw0mva6ckm8ww93b71shd9hsske0","pushDate":"2023-03-28 02:55:52.021809","url":"https://go.cvx.is/backend_release/0.0.326","version":"0.0.326"},
{"_creationTime":1691013604325.0142,"_id":"2ykm0sk01gg39y679gv0dmfw9hszfk0","pushDate":"2023-06-16 01:32:56.016600","url":"https://go.cvx.is/backend_release/0.0.388","version":"0.0.388"},
{"_creationTime":1691013604325.0222,"_id":"2ypm0a7r2hcc04f2jt2b6vcn9hsx3vr","pushDate":"2023-05-08 18:45:54.201856","url":"https://go.cvx.is/backend_release/0.0.357","version":"0.0.357"},
{"_creationTime":1691013604325.0183,"_id":"2ypq9926rw1yff7jhs13awk79hshxkr","pushDate":"2023-05-26 19:03:19.662893","url":"https://go.cvx.is/backend_release/0.0.370","version":"0.0.370"},
{"_creationTime":1691013604325.0283,"_id":"2ysb9x7pkeesn8zamx0cgyrr9hswemr","pushDate":"2023-03-27 19:05:15.015998","url":"https://go.cvx.is/backend_release/0.0.328","version":"0.0.328"},
{"_creationTime":1691013604325.023,"_id":"2ysbz87t8tjsqck914m668qt9hsk5r0","pushDate":"2023-04-28 21:04:38.536629","url":"https://go.cvx.is/backend_release/0.0.353","version":"0.0.353"},
{"_creationTime":1691013604325.032,"_id":"2yt2c6x92w04kfqt88c0me8a9hsk668","pushDate":"2023-02-27 22:58:12.934198","url":"https://go.cvx.is/backend_release/0.0.308","version":"0.0.308"},
{"_creationTime":1691013604325.0225,"_id":"2ytdatyqn3kpa9241petwagk9hss518","pushDate":"2023-05-02 21:15:24.107127","url":"https://go.cvx.is/backend_release/0.0.356","version":"0.0.356"},
{"_creationTime":1691013604325.0164,"_id":"2ytxnxct7hg330qnkysmq7589hshjqg","pushDate":"2023-06-08 20:28:09.710279","url":"https://go.cvx.is/backend_release/0.0.382","version":"0.0.382"},
{"_creationTime":1691013604325.0215,"_id":"2yv6vr9vsd7a4cmqcfvbm35z9hsqfng","pushDate":"2023-05-12 05:18:09.765552","url":"https://go.cvx.is/backend_release/0.0.359","version":"0.0.359"},
{"_creationTime":1691013604325.0315,"_id":"2yxdjq1aat2sxzpa6ky8wqrf9hsnszr","pushDate":"2023-03-03 20:42:52.129710","url":"https://go.cvx.is/backend_release/0.0.311","version":"0.0.311"},
{"_creationTime":1691013604325.0251,"_id":"2yz0dem43648azzd21hnyx7k9hst61r","pushDate":"2023-04-12 23:39:43.692199","url":"https://go.cvx.is/backend_release/0.0.344","version":"0.0.344"},
{"_creationTime":1691013604325.0295,"_id":"2z0dzdjgdmnkmckb51gbzhnj9hstjer","pushDate":"2023-03-20 17:25:27.224338","url":"https://go.cvx.is/backend_release/0.0.322","version":"0.0.322"},
{"_creationTime":1691013604325.0261,"_id":"2z0tgmhc5sdwfk70czfdn4tg9hsvqe0","pushDate":"2023-04-08 01:09:26.862023","url":"https://go.cvx.is/backend_release/0.0.341","version":"0.0.341"},
{"_creationTime":1691013604325.0256,"_id":"2z12vfzmqmmgf6stwj05x3609hsmhn8","pushDate":"2023-04-12 21:43:55.823633","url":"https://go.cvx.is/backend_release/0.0.343","version":"0.0.343"},
{"_creationTime":1691013604325.0266,"_id":"2z17q3j7jtfwvydkmysdsh519hsk0yg","pushDate":"2023-04-07 22:36:51.507056","url":"https://go.cvx.is/backend_release/0.0.339","version":"0.0.339"},
{"_creationTime":1691013604325.014,"_id":"2z19ae9ys7d6ry6bbfp0sfgc9hsh780","pushDate":"2023-06-16 21:39:27.521177","url":"https://go.cvx.is/backend_release/0.0.389","version":"0.0.389"},
{"_creationTime":1691013604325.025,"_id":"2z4h9hyq1zxxr9mpp2gr8aq09hsx5a0","pushDate":"2023-04-18 00:23:53.940027","url":"https://go.cvx.is/backend_release/0.0.345","version":"0.0.345"},
{"_creationTime":1691013604325.024,"_id":"2z79ap8jj4np8y1gx1d7nqgb9hsh3a8","pushDate":"2023-04-24 17:06:30.951023","url":"https://go.cvx.is/backend_release/0.0.350","version":"0.0.350"},
{"_creationTime":1691013604325.027,"_id":"2z8fe1702j7kdsfjbevwm56w9hszt3g","pushDate":"2023-04-04 22:17:14.743353","url":"https://go.cvx.is/backend_release/0.0.335","version":"0.0.335"},
{"_creationTime":1691013604325.0159,"_id":"2z9692xd7h2thddjz8xqda2j9hsqjm8","pushDate":"2023-06-12 18:16:24.506026","url":"https://go.cvx.is/backend_release/0.0.384","version":"0.0.384"},
{"_creationTime":1691013604325.029,"_id":"2zbvgxbkq75h61gbzbz8a9q59hsqtrg","pushDate":"2023-03-21 21:04:07.515153","url":"https://go.cvx.is/backend_release/0.0.324","version":"0.0.324"},
{"_creationTime":1691013604325.0264,"_id":"2zbyt5wyemq6msnhk38achgm9hsxpzr","pushDate":"2023-04-08 00:04:13.031319","url":"https://go.cvx.is/backend_release/0.0.336","version":"0.0.336"},
{"_creationTime":1691013604325.0156,"_id":"2zcymm62vh36vhqjfzs02nfg9hstjyg","pushDate":"2023-06-13 22:10:12.785103","url":"https://go.cvx.is/backend_release/0.0.385","version":"0.0.385"},
{"_creationTime":1691013604325.0173,"_id":"2zdgevs5gdw5dnxh5rbrja2c9hspepg","pushDate":"2023-06-02 20:24:41.629428","url":"https://go.cvx.is/backend_release/0.0.378","version":"0.0.378"},
{"_creationTime":1691013604325.026,"_id":"2zhwbmcynzkpt1mv50t889ps9hsq0e8","pushDate":"2023-04-12 19:28:33.669910","url":"https://go.cvx.is/backend_release/0.0.342","version":"0.0.342"},
{"_creationTime":1691013604325.0186,"_id":"2zkj03ff11enpdm0f5jtrewa9hssw88","pushDate":"2023-05-26 17:43:58.827331","url":"https://go.cvx.is/backend_release/0.0.368","version":"0.0.368"},
{"_creationTime":1691013604325.011,"_id":"2znj8m30pwnpqrwrjsj7f9zt9hspygr","pushDate":"2023-07-11 21:16:45.970504","url":"https://go.cvx.is/backend_release/0.0.402","version":"0.0.402"},
{"_creationTime":1691013604325.008,"_id":"2zqf38hh8sbz2fs8zvv70r3s9hsvn88","pushDate":"2023-08-02 21:37:23.405074","url":"https://go.cvx.is/backend_release/0.0.416","version":"0.0.416"},
{"_creationTime":1691013604325.0168,"_id":"2zrkweg4zt5c55zexs6wx7fd9hstaqg","pushDate":"2023-06-05 22:48:49.446257","url":"https://go.cvx.is/backend_release/0.0.380","version":"0.0.380"},
{"_creationTime":1691013604325.0288,"_id":"2ztesryjr0n63541dfm49t399hsv66g","pushDate":"2023-03-22 21:08:52.704334","url":"https://go.cvx.is/backend_release/0.0.325","version":"0.0.325"},
{"_creationTime":1691013604325.0237,"_id":"2zw0gkh8mhdy7jw2qs59r2s19hsmp28","pushDate":"2023-04-25 16:50:13.571099","url":"https://go.cvx.is/backend_release/0.0.351","version":"0.0.351"},
{"_creationTime":1691013604325.0151,"_id":"2zz8whw83a77w8dj3h7n7yb59hsmdn8","pushDate":"2023-06-15 01:13:54.902714","url":"https://go.cvx.is/backend_release/0.0.385","version":"0.0.385"}
]
